v2raycli/__init__.py
v2raycli/__main__.py
v2raycli/dispatch.py
v2raycli/inbounds.py
v2raycli/log.py
v2raycli/routing.py
v2raycli/subscription.py
v2raycli/config/__init__.py
v2raycli/config/meta.py
v2raycli/entry/__init__.py
v2raycli/entry/base.py
v2raycli/entry/cli.py
v2raycli/entry/dispatch.py
v2raycli/entry/list.py
v2raycli/entry/run.py
v2raycli/execute/__init__.py
v2raycli/execute/check.py
v2raycli/execute/run.py
v2raycli/execute/v2ray.py
v2raycli/outbounds/__init__.py
v2raycli/outbounds/base.py
v2raycli/outbounds/freedom.py
v2raycli/outbounds/shadowsocks.py
v2raycli/outbounds/vmess.py
v2raycli/utils/__init__.py
v2raycli/utils/base64.py
v2raycli-0.1.1.dist-info/LICENSE
v2raycli-0.1.1.dist-info/METADATA
v2raycli-0.1.1.dist-info/WHEEL
v2raycli-0.1.1.dist-info/entry_points.txt
v2raycli-0.1.1.dist-info/top_level.txt
v2raycli-0.1.1.dist-info/RECORD
